jsee/__init__.py
jsee/jsee.py
jsee-0.0.4.data/scripts/jsee
jsee-0.0.4.dist-info/METADATA
jsee-0.0.4.dist-info/WHEEL
jsee-0.0.4.dist-info/top_level.txt
jsee-0.0.4.dist-info/RECORD
