Metadata-Version: 2.1
Name: jsee
Version: 0.0.4
Summary: Simple GUI for processing tasks
Home-page: https://github.com/jseeio/jsee-py
Author: Anton Zemlyansky
Author-email: anton@zemlyansky.com
License: MIT
Platform: UNKNOWN
Classifier: Programming Language :: Python :: 3
Classifier: License :: OSI Approved :: MIT License
Classifier: Operating System :: OS Independent
Requires-Dist: flask
Requires-Dist: waitress
